Workbook

Sheet INSTRUCTIONS
B2: INSTRUCTIONS
B3: Alliance CFO Solutions
B5: STEP 1: Export from QuickBooks Online
B6: • Profit & Loss by Month (trailing 12 months)
B7: • Balance Sheet (current month)
B8: • A/R Aging Summary
B9: • A/P Aging Summary
B11: STEP 2: Paste into DATA_INPUT tab
B12: • P&L data: Row 2+ with Account Name in A, months in B-M
B13: • Balance Sheet: Starting at row indicated by 'BALANCE SHEET' marker
B14: • AR Aging: Starting at row indicated by 'AR AGING' marker
B15: • AP Aging: Starting at row indicated by 'AP AGING' marker
... B21: STEP 4: Review DASHBOARD tab for KPIs and trends

Sheet DATA_INPUT
A1: P&L DATA
A2: Account Name | B2: Jan | C2: Feb | D2: Mar | E2: Apr | F2: May | G2: Jun | H2: Jul | I2: Aug | J2: Sep | K2: Oct | L2: Nov | M2: Dec
A3: Revenue
A4: COGS
A5: Gross Profit
A6: Operating Expenses
A7: Operating Income
A8: Other Income/Expense
A9: Net Income
A12: BALANCE SHEET DATA
A13: Account | B13: Current Month | C13: Prior Month
A14: Cash
A15: Accounts Receivable
A16: Other Current Assets
A17: Total Current Assets
A18: Total Assets
A19: Accounts Payable
A20: Other Current Liabilities
A21: Total Current Liabilities
A22: Total Liabilities
A23: Total Equity
A25: AR AGING
B26: Current | C26: 1-30 | D26: 31-60 | E26: 61-90 | F26: 90+ | G26: Total
A27: Amount
A29: AP AGING
B30: Current | C30: 1-30 | D30: 31-60 | E30: 61-90 | F30: 90+ | G30: Total
A31: Amount

Sheet SETTINGS
A1: SETTINGS
A3: Company Name | B3: [Enter Company]
A4: Industry | B4: Service
A5: Number of Employees | B5: 10
A7: KPI TARGETS & RAG THRESHOLDS
A8: KPI | B8: Target | C8: Green Threshold | D8: Amber Threshold | E8: Red Threshold
A9: Revenue Growth (MoM) | B9: 5% | C9: 5% | D9: 0% | E9: -5%
A10: Gross Margin % | B10: 50% | C10: 45% | D10: 35% | E10: 25%
A11: Net Margin % | B11: 15% | C11: 10% | D11: 5% | E11: 0%
A12: Operating Expense Ratio | B12: 40% | C12: 45% | D12: 55% | E12: 65%
A13: Current Ratio | B13: 2.0 | C13: 1.5 | D13: 1.0 | E13: 0.8
A14: Quick Ratio | B14: 1.5 | C14: 1.0 | D14: 0.75 | E14: 0.5
A15: AR Days | B15: 30 | C15: 30 | D15: 45 | E15: 60
A16: AP Days | B16: 30 | C16: 30 | D16: 45 | E16: 60
A17: Cash Conversion Cycle | B17: 30 | C17: 30 | D17: 45 | E17: 60
A18: Revenue per Employee | B18: $15,000 | C18: $15,000 | D18: $10,000 | E18: $7,500
A19: Overhead Rate | B19: 25% | C19: 30% | D19: 40% | E19: 50%

Sheet DASHBOARD
A1: KPI DASHBOARD
A2: Company: | B2: =SETTINGS!B3
A4: 12-MONTH TRENDS
A5: Metric | B5: Jan | C5: Feb | D5: Mar | E5: Apr | F5: May | G5: Jun | H5: Jul | I5: Aug | J5: Sep | K5: Oct | L5: Nov | M5: Dec
A6: Revenue | B6: =DATA_INPUT!B3 | C6: =DATA_INPUT!C3 | D6: =DATA_INPUT!D3 | E6: =DATA_INPUT!E3 | F6: =DATA_INPUT!F3 | G6: =DATA_INPUT!G3 | H6: =DATA_INPUT!H3 | I6: =DATA_INPUT!I3 | ... M6: =DATA_INPUT!M3
A7: Gross Margin % | B7: =IF(DATA_INPUT!B3=0,0,DATA_INPUT!B5/DATA_INPUT!B3) | C7: =IF(DATA_INPUT!C3=0,0,DATA_INPUT!C5/DATA_INPUT!C3) | D7: =IF(DATA_INPUT!D3=0,0,DATA_INPUT!D5/DATA_INPUT!D3) | E7: =IF(DATA_INPUT!E3=0,0,DATA_INPUT!E5/DATA_INPUT!E3) | F7: =IF(DATA_INPUT!F3=0,0,DATA_INPUT!F5/DATA_INPUT!F3) | G7: =IF(DATA_INPUT!G3=0,0,DATA_INPUT!G5/DATA_INPUT!G3) | H7: =IF(DATA_INPUT!H3=0,0,DATA_INPUT!H5/DATA_INPUT!H3) | I7: =IF(DATA_INPUT!I3=0,0,DATA_INPUT!I5/DATA_INPUT!I3) | ... M7: =IF(DATA_INPUT!M3=0,0,DATA_INPUT!M5/DATA_INPUT!M3)
A8: Net Margin % | B8: =IF(DATA_INPUT!B3=0,0,DATA_INPUT!B9/DATA_INPUT!B3) | C8: =IF(DATA_INPUT!C3=0,0,DATA_INPUT!C9/DATA_INPUT!C3) | D8: =IF(DATA_INPUT!D3=0,0,DATA_INPUT!D9/DATA_INPUT!D3) | E8: =IF(DATA_INPUT!E3=0,0,DATA_INPUT!E9/DATA_INPUT!E3) | F8: =IF(DATA_INPUT!F3=0,0,DATA_INPUT!F9/DATA_INPUT!F3) | G8: =IF(DATA_INPUT!G3=0,0,DATA_INPUT!G9/DATA_INPUT!G3) | H8: =IF(DATA_INPUT!H3=0,0,DATA_INPUT!H9/DATA_INPUT!H3) | I8: =IF(DATA_INPUT!I3=0,0,DATA_INPUT!I9/DATA_INPUT!I3) | ... M8: =IF(DATA_INPUT!M3=0,0,DATA_INPUT!M9/DATA_INPUT!M3)
A9: Cash Balance | B9: =DATA_INPUT!B14 | C9: =DATA_INPUT!B14 | D9: =DATA_INPUT!B14 | E9: =DATA_INPUT!B14 | F9: =DATA_INPUT!B14 | G9: =DATA_INPUT!B14 | H9: =DATA_INPUT!B14 | I9: =DATA_INPUT!B14 | J9: =DATA_INPUT!B14 | K9: =DATA_INPUT!B14 | L9: =DATA_INPUT!B14 | M9: =DATA_INPUT!B14
A11: CURRENT MONTH KPIs
A12: KPI | B12: Value | C12: Target | D12: Status | E12: RAG
A13: Revenue Growth (MoM) | D13: — | E13: —
A14: Gross Margin % | D14: — | E14: —
A15: Net Margin % | D15: — | E15: —
A16: Operating Expense Ratio | D16: — | E16: —
A17: Current Ratio | D17: — | E17: —
A18: Quick Ratio | D18: — | E18: —
A19: AR Days Outstanding | D19: — | E19: —
A20: AP Days Outstanding | D20: — | E20: —
A21: Cash Conversion Cycle | D21: — | E21: —
A22: Revenue per Employee | D22: — | E22: —
A23: Overhead Rate | D23: — | E23: —
