Workbook

Sheet CALCULATOR
A1: ENGAGEMENT PRICING CALCULATOR
A3: Client Name: | B3: [Enter Client]
A5: ESTIMATED HOURS PER MONTH
A6: Activity | B6: Hours/Month
A7: Monthly close review
A8: Financial package prep
A9: Strategy calls
A10: Cash flow forecasting
A11: KPI dashboard maintenance
A12: Ad hoc support
A13: Lender/investor prep
A14: TOTAL HOURS | B14: =SUM(B7:B13)
A16: EFFECTIVE RATE BY TIER
A17: Tier | B17: Price | C17: Eff. Rate | D17: Margin
A18: Tier 1 — Essentials | B18: =SETTINGS!B9 | C18: =IF(B14=0,0,B18/B14) | D18: =IF(B18=0,0,(B18-(B14*SETTINGS!B3))/B18)
A19: Tier 2 — Growth | B19: =SETTINGS!B10 | C19: =IF(B14=0,0,B19/B14) | D19: =IF(B19=0,0,(B19-(B14*SETTINGS!B3))/B19)
A20: Tier 3 — Scale | B20: =SETTINGS!B11 | C20: =IF(B14=0,0,B20/B14) | D20: =IF(B20=0,0,(B20-(B14*SETTINGS!B3))/B20)
A21: Tier 4 — Enterprise | B21: =SETTINGS!B12 | C21: =IF(B14=0,0,B21/B14) | D21: =IF(B21=0,0,(B21-(B14*SETTINGS!B3))/B21)
A23: RECOMMENDED TIER
A24: Based on hours: | B24: =IF(B14<=12,"Tier 1 — Essentials",IF(B14<=22,"Tier 2 — Growth",IF(B14<=40,"Tier 3 — Scale","Tier 4 — Enterprise")))
A26: PROFITABILITY ANALYSIS
A27: Projected Revenue (Recommended Tier): | B27: =IF(B14<=12,SETTINGS!B9,IF(B14<=22,SETTINGS!B10,IF(B14<=40,SETTINGS!B11,SETTINGS!B12)))
A28: Total Cost (hours × rate): | B28: =B14*SETTINGS!B3
A29: Monthly Profit: | B29: =B27-B28
A30: Margin %: | B30: =IF(B27=0,0,B29/B27)

Sheet SETTINGS
A1: PRICING SETTINGS
A3: Internal Cost Rate ($/hr) | B3: 75
A4: Target Utilization % | B4: 0.8
A5: Target Margin % | B5: 0.5
A7: TIER PRICING
A8: Tier | B8: Monthly Price | C8: Max Hours
A9: Tier 1 — Essentials | B9: 1500 | C9: 12
A10: Tier 2 — Growth | B10: 2500 | C10: 22
A11: Tier 3 — Scale | B11: 5000 | C11: 40
A12: Tier 4 — Enterprise | B12: 7500 | C12: 60

Sheet COMPARISON
A1: TIER COMPARISON
B3: Tier 1 | C3: Tier 2 | D3: Tier 3 | E3: Tier 4
A4: Monthly Price | B4: =SETTINGS!B9 | C4: =SETTINGS!B10 | D4: =SETTINGS!B11 | E4: =SETTINGS!B12
A5: Included Hours | B5: =SETTINGS!C9 | C5: =SETTINGS!C10 | D5: =SETTINGS!C11 | E5: =SETTINGS!C12
A6: Effective Rate | B6: =IF(B5=0,0,B4/B5) | C6: =IF(C5=0,0,C4/C5) | D6: =IF(D5=0,0,D4/D5) | E6: =IF(E5=0,0,E4/E5)
A7: Internal Cost | B7: =B5*SETTINGS!B3 | C7: =C5*SETTINGS!B3 | D7: =D5*SETTINGS!B3 | E7: =E5*SETTINGS!B3
A8: Monthly Profit | B8: =B4-B7 | C8: =C4-C7 | D8: =D4-D7 | E8: =E4-E7
A9: Margin % | B9: =IF(B4=0,0,B8/B4) | C9: =IF(C4=0,0,C8/C4) | D9: =IF(D4=0,0,D8/D4) | E9: =IF(E4=0,0,E8/E4)
A11: BREAK-EVEN ANALYSIS
A12: Break-even Hours | B12: =IF(SETTINGS!B3=0,0,B4/SETTINGS!B3) | C12: =IF(SETTINGS!B3=0,0,C4/SETTINGS!B3) | D12: =IF(SETTINGS!B3=0,0,D4/SETTINGS!B3) | E12: =IF(SETTINGS!B3=0,0,E4/SETTINGS!B3)
